{
  "version": "0.11.0-dev.1404+562d52e23",
  "date": "2023-01-22",
  "docs": "https://ziglang.org/documentation/master/",
  "stdDocs": "https://ziglang.org/documentation/master/std/",
  "src": {
    "tarball": "https://ziglang.org/builds/zig-0.11.0-dev.1404+562d52e23.tar.xz",
    "shasum": "ba1c16d17c6eb943a2259f53f9c9d177c2b3f88b2278251360cd526c3fa07981",
    "size": "14504264"
  },
  "bootstrap": {
    "tarball": "https://ziglang.org/builds/zig-bootstrap-0.11.0-dev.1404+562d52e23.tar.xz",
    "shasum": "20d5d382990b64b08eb18c770ea5d80f7afefa2e31a9f7b84b190aa3e4dc4c9c",
    "size": "44249352"
  },
  "x86_64-macos": {
    "tarball": "https://ziglang.org/builds/zig-macos-x86_64-0.11.0-dev.1404+562d52e23.tar.xz",
    "shasum": "895315d82da9695d1abaf50f3444240d002daee3a366e15f3c2aad0160e6bf6b",
    "size": "43248592"
  },
  "aarch64-macos": {
    "tarball": "https://ziglang.org/builds/zig-macos-aarch64-0.11.0-dev.1404+562d52e23.tar.xz",
    "shasum": "2703bca4e53a3f90bb16f354f8b2a87757290e68ec294ab0442e744665bd7bf0",
    "size": "38601372"
  },
  "x86_64-linux": {
    "tarball": "https://ziglang.org/builds/zig-linux-x86_64-0.11.0-dev.1404+562d52e23.tar.xz",
    "shasum": "e2510a20e75131f9ed283e99c953f694a2c7f4caf8acb7fce7cacbc89c99a2bd",
    "size": "42373608"
  },
  "aarch64-linux": {
    "tarball": "https://ziglang.org/builds/zig-linux-aarch64-0.11.0-dev.1404+562d52e23.tar.xz",
    "shasum": "3c5b4d0faab12d7e5bd9cc2e91fb82c979e96a3caed49ab622a46dbc7bb41435",
    "size": "38852508"
  },
  "riscv64-linux": {
    "tarball": "https://ziglang.org/builds/zig-linux-riscv64-0.11.0-dev.1404+562d52e23.tar.xz",
    "shasum": "95f51da0645a636fb7b2b91e9992c9be7d725d31cfcd390d9300e35c3a9fa55c",
    "size": "40708252"
  },
  "powerpc64le-linux": {
    "tarball": "https://ziglang.org/builds/zig-linux-powerpc64le-0.11.0-dev.1404+562d52e23.tar.xz",
    "shasum": "dea446c69224668a76f9ca4a1162c046c8e6e2b74abbdf1f94c9a9e35ef2b6ac",
    "size": "42374688"
  },
  "powerpc-linux": {
    "tarball": "https://ziglang.org/builds/zig-linux-powerpc-0.11.0-dev.1404+562d52e23.tar.xz",
    "shasum": "ba76e847e656c836a62e11dc1ca03e00b1fa81d7d213a4738a9ca0840bba33db",
    "size": "41847144"
  },
  "x86-linux": {
    "tarball": "https://ziglang.org/builds/zig-linux-x86-0.11.0-dev.1404+562d52e23.tar.xz",
    "shasum": "43904d575ccf75bc03e7d1c354a32f430640c81a1c84503e43ea363a1ea50ae2",
    "size": "46654540"
  },
  "x86_64-windows": {
    "tarball": "https://ziglang.org/builds/zig-windows-x86_64-0.11.0-dev.1404+562d52e23.zip",
    "shasum": "7587c118080f09561a383b5df0131128fcc3b8a59199cfc052503e6ef6e25b75",
    "size": "74201764"
  },
  "aarch64-windows": {
    "tarball": "https://ziglang.org/builds/zig-windows-aarch64-0.11.0-dev.1404+562d52e23.zip",
    "shasum": "e6efaa6e08c5ae69c92cadf75f66a50de04a8968d9207234a3631c88adfd80c5",
    "size": "70297119"
  },
  "x86-windows": {
    "tarball": "https://ziglang.org/builds/zig-windows-x86-0.11.0-dev.1404+562d52e23.zip",
    "shasum": "2773a685c2dbc309bce3df634ce9f00d5a4bbf7da90531073a054254ab031741",
    "size": "77632522"
  }
}
