{
  "version": "0.10.0-dev.4249+11dce7894",
  "date": "2022-10-06",
  "docs": "https://ziglang.org/documentation/master/",
  "stdDocs": "https://ziglang.org/documentation/master/std/",
  "src": {
    "tarball": "https://ziglang.org/builds/zig-0.10.0-dev.4249+11dce7894.tar.xz",
    "shasum": "081366a210f8bfc74c2585476011b4acb8480ff24dd1d968477cd938934aa30c",
    "size": "15825808"
  },
  "x86_64-freebsd": {
    "tarball": "https://ziglang.org/builds/zig-freebsd-x86_64-0.10.0-dev.4249+11dce7894.tar.xz",
    "shasum": "c739690d15367f6e0ac150dac84e4b1f707bb2c402801dd779076ffc301aad96",
    "size": "40956020"
  },
  "x86_64-macos": {
    "tarball": "https://ziglang.org/builds/zig-macos-x86_64-0.10.0-dev.4249+11dce7894.tar.xz",
    "shasum": "62f3651068a2575ce8120ef448b1d88adcc0a2b9e10ea30163a8f8931f0a96c0",
    "size": "44155628"
  },
  "aarch64-macos": {
    "tarball": "https://ziglang.org/builds/zig-macos-aarch64-0.10.0-dev.4249+11dce7894.tar.xz",
    "shasum": "210aaf20e88c013a3eb57e719fade0313e544bc8fb69b465d5d6092895e3a2fd",
    "size": "40970844"
  },
  "x86_64-windows": {
    "tarball": "https://ziglang.org/builds/zig-windows-x86_64-0.10.0-dev.4249+11dce7894.zip",
    "shasum": "35c7bb7634187f49dab4f687f46fac46321e00d8340c1f97613d5e9a67dbeab6",
    "size": "69144885"
  },
  "x86_64-linux": {
    "tarball": "https://ziglang.org/builds/zig-linux-x86_64-0.10.0-dev.4249+11dce7894.tar.xz",
    "shasum": "357580ee687a2eb694a02109be0c8149a1717f2d7e979a0167bc52ac513f7741",
    "size": "44178432"
  },
  "aarch64-linux": {
    "tarball": "https://ziglang.org/builds/zig-linux-aarch64-0.10.0-dev.4249+11dce7894.tar.xz",
    "shasum": "fc51c9700098636770facce8b31828f37f8f385764d433f488fc4a47f08394d2",
    "size": "38043716"
  }
}
