{
  "version": "0.10.0-dev.4451+5ec76cf5c",
  "date": "2022-10-18",
  "docs": "https://ziglang.org/documentation/master/",
  "stdDocs": "https://ziglang.org/documentation/master/std/",
  "src": {
    "tarball": "https://ziglang.org/builds/zig-0.10.0-dev.4451+5ec76cf5c.tar.xz",
    "shasum": "cfdff6c1eb463b85b70f4370d9b3afb8533710b7c2529d32635c4828763dd62e",
    "size": "15937616"
  },
  "x86_64-freebsd": {
    "tarball": "https://ziglang.org/builds/zig-freebsd-x86_64-0.10.0-dev.4451+5ec76cf5c.tar.xz",
    "shasum": "5dd6a930191da38a80c36d7e3b1df6212b4d7742baf643d781313b53256ab30d",
    "size": "41072088"
  },
  "x86_64-macos": {
    "tarball": "https://ziglang.org/builds/zig-macos-x86_64-0.10.0-dev.4451+5ec76cf5c.tar.xz",
    "shasum": "49d9dadd7dd8b3f833551b08da75c794db7f82b4bcf2392d2083f8c23639c215",
    "size": "44175980"
  },
  "aarch64-macos": {
    "tarball": "https://ziglang.org/builds/zig-macos-aarch64-0.10.0-dev.4451+5ec76cf5c.tar.xz",
    "shasum": "a996a21cf6b10b9d962e14439528bcb205a0e3e1a2a3673baedc8e5dc12c0019",
    "size": "41031936"
  },
  "x86_64-windows": {
    "tarball": "https://ziglang.org/builds/zig-windows-x86_64-0.10.0-dev.4451+5ec76cf5c.zip",
    "shasum": "873645c023c49afb8da5d55c888552e1883f5b89571621ad7d4f55867efa1cd9",
    "size": "69321334"
  },
  "x86_64-linux": {
    "tarball": "https://ziglang.org/builds/zig-linux-x86_64-0.10.0-dev.4451+5ec76cf5c.tar.xz",
    "shasum": "7c8b513e53e9036d22baf2c2f102249934cb058d1408f978033e39899ce9ae86",
    "size": "44313452"
  },
  "aarch64-linux": {
    "tarball": "https://ziglang.org/builds/zig-linux-aarch64-0.10.0-dev.4451+5ec76cf5c.tar.xz",
    "shasum": "82a8a6da6c65f45ab615a18bc7876428b06bb8c1eed3e85f341086328685f8aa",
    "size": "37450760"
  }
}
