{
  "version": "0.10.0-dev.2473+e498fb155",
  "date": "2022-06-02",
  "docs": "https://ziglang.org/documentation/master/",
  "stdDocs": "https://ziglang.org/documentation/master/std/",
  "src": {
    "tarball": "https://ziglang.org/builds/zig-0.10.0-dev.2473+e498fb155.tar.xz",
    "shasum": "0ae097caee75888af2f4eca06dbb3b37ad327b15ca0024e937b23eada1d31fbc",
    "size": "15767240"
  },
  "x86_64-freebsd": {
    "tarball": "https://ziglang.org/builds/zig-freebsd-x86_64-0.10.0-dev.2473+e498fb155.tar.xz",
    "shasum": "fbee9e839793b0d0847fcc1699fc0b6459764ab4380ec8a05517c8a8d61202ae",
    "size": "44576716"
  },
  "x86_64-macos": {
    "tarball": "https://ziglang.org/builds/zig-macos-x86_64-0.10.0-dev.2473+e498fb155.tar.xz",
    "shasum": "ab58cceba715ee7dfeb6a35901cc27d5666d02de0637d73d0c2d85720dc09a5a",
    "size": "43205700"
  },
  "aarch64-macos": {
    "tarball": "https://ziglang.org/builds/zig-macos-aarch64-0.10.0-dev.2473+e498fb155.tar.xz",
    "shasum": "c0b4de0a3f42ee8a8c462aab57331418947592e698c8eca3be852b777102e134",
    "size": "40157324"
  },
  "x86_64-windows": {
    "tarball": "https://ziglang.org/builds/zig-windows-x86_64-0.10.0-dev.2473+e498fb155.zip",
    "shasum": "f72878a1580ba809d11db8d5783ebff1192331f6a4021ab8ecf429775ba0aa2a",
    "size": "64376662"
  },
  "x86_64-linux": {
    "tarball": "https://ziglang.org/builds/zig-linux-x86_64-0.10.0-dev.2473+e498fb155.tar.xz",
    "shasum": "610e5d3d52faaeaf19e8d2530af049ae0fb4b899d547a0a39e4e5d8abbf679c0",
    "size": "40451320"
  },
  "aarch64-linux": {
    "tarball": "https://ziglang.org/builds/zig-linux-aarch64-0.10.0-dev.2473+e498fb155.tar.xz",
    "shasum": "4c1630aac9a2dba915482c852f2d332a37a9f54cac6228db72b8eadba4ea8059",
    "size": "40687884"
  }
}
