{
  "version": "0.10.0-dev.3659+e5e6eb983",
  "date": "2022-08-20",
  "docs": "https://ziglang.org/documentation/master/",
  "stdDocs": "https://ziglang.org/documentation/master/std/",
  "src": {
    "tarball": "https://ziglang.org/builds/zig-0.10.0-dev.3659+e5e6eb983.tar.xz",
    "shasum": "822b4e6def26c686f96fe43426e4d461e9ce3f9bf1c500ffef17ba2521532f28",
    "size": "15934324"
  },
  "x86_64-freebsd": {
    "tarball": "https://ziglang.org/builds/zig-freebsd-x86_64-0.10.0-dev.3659+e5e6eb983.tar.xz",
    "shasum": "f1d263bd83c29806b7919e95a54c68127ba0cf7261b79b6e74f12dab15e5ffc2",
    "size": "40015668"
  },
  "x86_64-macos": {
    "tarball": "https://ziglang.org/builds/zig-macos-x86_64-0.10.0-dev.3659+e5e6eb983.tar.xz",
    "shasum": "a5e6d500dcb3c771eca30b639d53ec05bcd07880ba049b8a3de28e8810f17646",
    "size": "43273228"
  },
  "aarch64-macos": {
    "tarball": "https://ziglang.org/builds/zig-macos-aarch64-0.10.0-dev.3659+e5e6eb983.tar.xz",
    "shasum": "d230f5871e21e70df2ae1028978eb23d1684a866ce4dd418608e3327fd40efdd",
    "size": "40240216"
  },
  "x86_64-windows": {
    "tarball": "https://ziglang.org/builds/zig-windows-x86_64-0.10.0-dev.3659+e5e6eb983.zip",
    "shasum": "acb54feb3f5c284aac6853cdc7f4e3ade33eb6792205ddd043075d8c4ece5968",
    "size": "67501937"
  },
  "x86_64-linux": {
    "tarball": "https://ziglang.org/builds/zig-linux-x86_64-0.10.0-dev.3659+e5e6eb983.tar.xz",
    "shasum": "7358576b8f4e503c04884ad7d399231674519fb12e09d97e3bec64ad76bca0e2",
    "size": "43321556"
  },
  "aarch64-linux": {
    "tarball": "https://ziglang.org/builds/zig-linux-aarch64-0.10.0-dev.3659+e5e6eb983.tar.xz",
    "shasum": "ae2b6df070eaf4c6d0062cccf27206cd716aa9e12f45e14818b3451494998e34",
    "size": "37102648"
  }
}
