{
  "version": "0.11.0-dev.2160+49d37e2d1",
  "date": "2023-03-19",
  "docs": "https://ziglang.org/documentation/master/",
  "stdDocs": "https://ziglang.org/documentation/master/std/",
  "src": {
    "tarball": "https://ziglang.org/builds/zig-0.11.0-dev.2160+49d37e2d1.tar.xz",
    "shasum": "62f097c09afb48cbf4a828b2111838a33a3d590f0b5e070ca9dffdb886585e11",
    "size": "14779464"
  },
  "bootstrap": {
    "tarball": "https://ziglang.org/builds/zig-bootstrap-0.11.0-dev.2160+49d37e2d1.tar.xz",
    "shasum": "89d65aceed1be8de24f0c6304629653222b9d0c9e0ce82c0dc807fc59ae4923a",
    "size": "44523156"
  },
  "x86_64-macos": {
    "tarball": "https://ziglang.org/builds/zig-macos-x86_64-0.11.0-dev.2160+49d37e2d1.tar.xz",
    "shasum": "8d4d6916ea90037d4a7ea1d903d09690930d4477a283eaaf2de22382851bc0b2",
    "size": "43700908"
  },
  "aarch64-macos": {
    "tarball": "https://ziglang.org/builds/zig-macos-aarch64-0.11.0-dev.2160+49d37e2d1.tar.xz",
    "shasum": "2bc19650da1ff75fe4e1359dc0f27239c87b3758a1c8a889a8e91816f9168dac",
    "size": "39018020"
  },
  "x86_64-linux": {
    "tarball": "https://ziglang.org/builds/zig-linux-x86_64-0.11.0-dev.2160+49d37e2d1.tar.xz",
    "shasum": "ad012e4736f2aa55005e32929bcefde7474c674a9ff280c16d49dccfac35e819",
    "size": "42869196"
  },
  "aarch64-linux": {
    "tarball": "https://ziglang.org/builds/zig-linux-aarch64-0.11.0-dev.2160+49d37e2d1.tar.xz",
    "shasum": "50de11550c60a84d4cc69a749ee89cc1d92f24789600d04019aad70b1bfd202e",
    "size": "39353272"
  },
  "riscv64-linux": {
    "tarball": "https://ziglang.org/builds/zig-linux-riscv64-0.11.0-dev.2160+49d37e2d1.tar.xz",
    "shasum": "4573cd16f805abca019891b384cc4fe98c5e4510c39aabe9399d6fbb0b598ca9",
    "size": "41235480"
  },
  "powerpc64le-linux": {
    "tarball": "https://ziglang.org/builds/zig-linux-powerpc64le-0.11.0-dev.2160+49d37e2d1.tar.xz",
    "shasum": "756a6ba4154f4ac6066f0c6c5b615779cb81de9bb8f1448f3673cb7e6d960b70",
    "size": "42713684"
  },
  "powerpc-linux": {
    "tarball": "https://ziglang.org/builds/zig-linux-powerpc-0.11.0-dev.2160+49d37e2d1.tar.xz",
    "shasum": "52219bc985b6c7a0d91dd428e628db9ce7abf90ec797cdc69d9da33b9f19f907",
    "size": "42299216"
  },
  "x86-linux": {
    "tarball": "https://ziglang.org/builds/zig-linux-x86-0.11.0-dev.2160+49d37e2d1.tar.xz",
    "shasum": "15eee749877b06bb9499a6ff3370b40458f8c53a073508ea073974abc8968a55",
    "size": "47128732"
  },
  "x86_64-windows": {
    "tarball": "https://ziglang.org/builds/zig-windows-x86_64-0.11.0-dev.2160+49d37e2d1.zip",
    "shasum": "299abd7b3b0eaa9783f4c049e8ce7b89b0a2aacbcedc80916c0d24dd9ca80595",
    "size": "74992403"
  },
  "aarch64-windows": {
    "tarball": "https://ziglang.org/builds/zig-windows-aarch64-0.11.0-dev.2160+49d37e2d1.zip",
    "shasum": "8c89e0df6920bad472dfe483f98ad3328eb4baa215cb0c1f3ce4ef6411b64b8b",
    "size": "71071030"
  },
  "x86-windows": {
    "tarball": "https://ziglang.org/builds/zig-windows-x86-0.11.0-dev.2160+49d37e2d1.zip",
    "shasum": "18744821b7d304d97140305009ecae7b5475063bb0aab7e9ff7ad1dc41d126be",
    "size": "78442021"
  }
}
