{
  "version": "0.10.0-dev.3021+b2486fbc5",
  "date": "2022-07-16",
  "docs": "https://ziglang.org/documentation/master/",
  "stdDocs": "https://ziglang.org/documentation/master/std/",
  "src": {
    "tarball": "https://ziglang.org/builds/zig-0.10.0-dev.3021+b2486fbc5.tar.xz",
    "shasum": "b3f18c7561a1599f7226a16c0a20b46e090f40f95868cbc1c36a7853348fba75",
    "size": "15881248"
  },
  "x86_64-freebsd": {
    "tarball": "https://ziglang.org/builds/zig-freebsd-x86_64-0.10.0-dev.3021+b2486fbc5.tar.xz",
    "shasum": "2e770cb60e0fb4e3f93708cdc966b21b8b7f7a8b94ece927edce2283afd2b134",
    "size": "45708200"
  },
  "x86_64-macos": {
    "tarball": "https://ziglang.org/builds/zig-macos-x86_64-0.10.0-dev.3021+b2486fbc5.tar.xz",
    "shasum": "67914e8d6952ccca3f3ac8269149b96193c1ed0169acdd368a64aa6502512d36",
    "size": "45713468"
  },
  "aarch64-macos": {
    "tarball": "https://ziglang.org/builds/zig-macos-aarch64-0.10.0-dev.3021+b2486fbc5.tar.xz",
    "shasum": "d6c032010e81c9c80f5814eec8311041be081682bdf97bf33050f04c23c52c46",
    "size": "41486148"
  },
  "x86_64-windows": {
    "tarball": "https://ziglang.org/builds/zig-windows-x86_64-0.10.0-dev.3021+b2486fbc5.zip",
    "shasum": "7327b195fab37fe097f30165bcb16545342b96a3f2092606d7e93cfd1644accd",
    "size": "65803600"
  },
  "x86_64-linux": {
    "tarball": "https://ziglang.org/builds/zig-linux-x86_64-0.10.0-dev.3021+b2486fbc5.tar.xz",
    "shasum": "6e20b7ad339979537eb6c885a24f0f569fc4b1f1561d0260d9efe23895004dc1",
    "size": "53967068"
  },
  "aarch64-linux": {
    "tarball": "https://ziglang.org/builds/zig-linux-aarch64-0.10.0-dev.3021+b2486fbc5.tar.xz",
    "shasum": "68da86cf765cfd4e581ed67d3aed2d751d4bed4246998773dd2a8c320b37c31a",
    "size": "43316660"
  }
}
